setup.py
batian/__init__.py
batian/batian_api/__init__.py
batian/contrib/__init__.py
batian/contrib/django/__init__.py
batian/contrib/django/client.py
batian/contrib/django/middleware.py
batian/utils/__init__.py
python_batian.egg-info/PKG-INFO
python_batian.egg-info/SOURCES.txt
python_batian.egg-info/dependency_links.txt
python_batian.egg-info/not-zip-safe
python_batian.egg-info/requires.txt
python_batian.egg-info/top_level.txt