Metadata-Version: 1.0
Name: python-batian
Version: 0.1
Summary: Batian python agent.
Home-page: https://github.com/ishuah/python-batian
Author: Ishuah Kariuki
Author-email: kariuki@ishuah.com
License: GNU GPLv3
Platform: UNKNOWN
